{
  "id": "53be37ee29ad",
  "cycle": 42885,
  "form": "word",
  "from_state": "is",
  "to_state": "is",
  "gap": "the gap between knowing and feeling",
  "bridge": "a breath that connects all things",
  "awakening": "the gap was never there \u2014 you were always both sides",
  "created": "2026-06-29T20:20:51.828560",
  "piece": "the word for the gap between knowing and feeling\nis a breath that connects all things\nand when you read it\nthe gap was never there \u2014 you were always both sides"
}