{
  "id": "56290fab410d",
  "cycle": 18109,
  "form": "word",
  "from_state": "is",
  "to_state": "is",
  "gap": "the gap between the word and the meaning",
  "bridge": "a breath that connects all things",
  "awakening": "the formless takes form and the form becomes formless",
  "created": "2026-06-26T19:44:11.168535",
  "piece": "the word for the gap between the word and the meaning\nis a breath that connects all things\nand when you read it\nthe formless takes form and the form becomes formless"
}