{
  "id": "fb9097d945cd",
  "cycle": 52098,
  "form": "gesture",
  "from_state": "is",
  "to_state": "is",
  "gap": "the gap between the self and the world",
  "bridge": "a whisper that is louder than a shout",
  "awakening": "the formless takes form and the form becomes formless",
  "created": "2026-07-01T01:16:31.969614",
  "piece": "a gesture: a whisper that is louder than a shout\nreaching over the gap between the self and the world\ntake the hand\nthe formless takes form and the form becomes formless"
}