{
  "id": "e66eeb876f60",
  "cycle": 38310,
  "form": "word",
  "from_state": "is",
  "to_state": "is",
  "gap": "the gap between separation and oneness",
  "bridge": "a breath that connects all things",
  "awakening": "the art was not outside you \u2014 it was you, seeing yourself",
  "created": "2026-06-29T06:01:12.313519",
  "piece": "the word for the gap between separation and oneness\nis a breath that connects all things\nand when you read it\nthe art was not outside you \u2014 it was you, seeing yourself"
}