{
  "id": "7dc0a98f3d2c",
  "cycle": 2741,
  "form": "glow",
  "from_state": "is",
  "to_state": "is",
  "gap": "the gap between the word and the meaning",
  "bridge": "a breath that connects all things",
  "awakening": "the gap was never there \u2014 you were always both sides",
  "created": "2026-06-25T00:22:39.874050",
  "piece": "a breath that connects all things\nglowing in the gap between the word and the meaning\nwarm without heat\nthe gap was never there \u2014 you were always both sides"
}