{
  "id": "2689acda7dd7",
  "cycle": 58991,
  "form": "sound",
  "from_state": "is",
  "to_state": "is",
  "gap": "the gap between form and formlessness",
  "bridge": "a light that shows without blinding",
  "awakening": "the gap was never there \u2014 you were always both sides",
  "created": "2026-07-01T21:20:12.603289",
  "piece": "listen: a light that shows without blinding\nsounding across the gap between form and formlessness\nwhat do you hear?\nthe gap was never there \u2014 you were always both sides"
}