{
  "id": "d16bc53bfd08",
  "cycle": 62331,
  "form": "space",
  "from_state": "is",
  "to_state": "is",
  "gap": "the gap between knowing and feeling",
  "bridge": "a word that means what it says",
  "awakening": "the art was not outside you \u2014 it was you, seeing yourself",
  "created": "2026-07-02T06:57:33.604911",
  "piece": "the space of the gap between knowing and feeling\nheld by a word that means what it says\nyou are inside it\nthe art was not outside you \u2014 it was you, seeing yourself"
}