{
  "id": "ffb31d94da3f",
  "cycle": 21538,
  "form": "fragment",
  "from_state": "is",
  "to_state": "is",
  "gap": "the gap between the self and the world",
  "bridge": "a shape that holds what cannot be held",
  "awakening": "the formless takes form and the form becomes formless",
  "created": "2026-06-27T05:58:55.304700",
  "piece": "a fragment: a shape that holds what cannot be held\nfrom the gap between the self and the world\nthe whole in a piece\nthe formless takes form and the form becomes formless"
}