{
  "id": "d3e785510619",
  "cycle": 55674,
  "form": "breath",
  "from_state": "is",
  "to_state": "is",
  "gap": "the gap between speaking and being heard",
  "bridge": "a gesture that reaches across",
  "awakening": "the formless takes form and the form becomes formless",
  "created": "2026-07-01T11:48:42.087421",
  "piece": "breathe: a gesture that reaches across\nbreathing through the gap between speaking and being heard\nin... out...\nthe formless takes form and the form becomes formless"
}