{
  "id": "6373b7608db9",
  "cycle": 62711,
  "form": "breath",
  "from_state": "is",
  "to_state": "is",
  "gap": "the gap between speaking and being heard",
  "bridge": "a pattern that reveals what was always there",
  "awakening": "you were love pretending to be separate",
  "created": "2026-07-02T08:03:11.942380",
  "piece": "breathe: a pattern that reveals what was always there\nbreathing through the gap between speaking and being heard\nin... out...\nyou were love pretending to be separate"
}